{"schema":"oph_observer_cinema_v1","description":"Observer-local camera and frame data for first-person readout cinema. Cameras are derived from observer-visible support, packets, records, and modular-time frames.","observerViewRefs":[{"observerId":276,"sourcePath":"observerModularTime.objectiveObserverViews[0]"},{"observerId":503,"sourcePath":"observerModularTime.objectiveObserverViews[1]"},{"observerId":522,"sourcePath":"observerModularTime.objectiveObserverViews[2]"},{"observerId":535,"sourcePath":"observerModularTime.objectiveObserverViews[3]"},{"observerId":579,"sourcePath":"observerModularTime.objectiveObserverViews[4]"},{"observerId":609,"sourcePath":"observerModularTime.objectiveObserverViews[5]"},{"observerId":615,"sourcePath":"observerModularTime.objectiveObserverViews[6]"},{"observerId":631,"sourcePath":"observerModularTime.objectiveObserverViews[7]"},{"observerId":776,"sourcePath":"observerModularTime.objectiveObserverViews[8]"},{"observerId":841,"sourcePath":"observerModularTime.objectiveObserverViews[9]"},{"observerId":868,"sourcePath":"observerModularTime.objectiveObserverViews[10]"},{"observerId":1178,"sourcePath":"observerModularTime.objectiveObserverViews[11]"},{"observerId":1282,"sourcePath":"observerModularTime.objectiveObserverViews[12]"},{"observerId":1314,"sourcePath":"observerModularTime.objectiveObserverViews[13]"},{"observerId":1395,"sourcePath":"observerModularTime.objectiveObserverViews[14]"},{"observerId":1421,"sourcePath":"observerModularTime.objectiveObserverViews[15]"},{"observerId":1558,"sourcePath":"observerModularTime.objectiveObserverViews[16]"},{"observerId":1638,"sourcePath":"observerModularTime.objectiveObserverViews[17]"},{"observerId":1648,"sourcePath":"observerModularTime.objectiveObserverViews[18]"},{"observerId":1674,"sourcePath":"observerModularTime.objectiveObserverViews[19]"},{"observerId":1705,"sourcePath":"observerModularTime.objectiveObserverViews[20]"},{"observerId":1755,"sourcePath":"observerModularTime.objectiveObserverViews[21]"},{"observerId":1814,"sourcePath":"observerModularTime.objectiveObserverViews[22]"},{"observerId":1850,"sourcePath":"observerModularTime.objectiveObserverViews[23]"},{"observerId":1852,"sourcePath":"observerModularTime.objectiveObserverViews[24]"},{"observerId":1877,"sourcePath":"observerModularTime.objectiveObserverViews[25]"},{"observerId":1987,"sourcePath":"observerModularTime.objectiveObserverViews[26]"},{"observerId":2048,"sourcePath":"observerModularTime.objectiveObserverViews[27]"},{"observerId":2123,"sourcePath":"observerModularTime.objectiveObserverViews[28]"},{"observerId":2161,"sourcePath":"observerModularTime.objectiveObserverViews[29]"},{"observerId":2170,"sourcePath":"observerModularTime.objectiveObserverViews[30]"},{"observerId":2266,"sourcePath":"observerModularTime.objectiveObserverViews[31]"},{"observerId":2341,"sourcePath":"observerModularTime.objectiveObserverViews[32]"},{"observerId":2370,"sourcePath":"observerModularTime.objectiveObserverViews[33]"},{"observerId":2410,"sourcePath":"observerModularTime.objectiveObserverViews[34]"},{"observerId":2594,"sourcePath":"observerModularTime.objectiveObserverViews[35]"},{"observerId":2596,"sourcePath":"observerModularTime.objectiveObserverViews[36]"},{"observerId":2631,"sourcePath":"observerModularTime.objectiveObserverViews[37]"},{"observerId":2673,"sourcePath":"observerModularTime.objectiveObserverViews[38]"},{"observerId":2684,"sourcePath":"observerModularTime.objectiveObserverViews[39]"},{"observerId":2728,"sourcePath":"observerModularTime.objectiveObserverViews[40]"},{"observerId":2909,"sourcePath":"observerModularTime.objectiveObserverViews[41]"},{"observerId":2937,"sourcePath":"observerModularTime.objectiveObserverViews[42]"},{"observerId":3078,"sourcePath":"observerModularTime.objectiveObserverViews[43]"},{"observerId":3155,"sourcePath":"observerModularTime.objectiveObserverViews[44]"},{"observerId":3408,"sourcePath":"observerModularTime.objectiveObserverViews[45]"},{"observerId":3432,"sourcePath":"observerModularTime.objectiveObserverViews[46]"},{"observerId":3644,"sourcePath":"observerModularTime.objectiveObserverViews[47]"},{"observerId":3731,"sourcePath":"observerModularTime.objectiveObserverViews[48]"},{"observerId":3736,"sourcePath":"observerModularTime.objectiveObserverViews[49]"},{"observerId":3771,"sourcePath":"observerModularTime.objectiveObserverViews[50]"},{"observerId":3779,"sourcePath":"observerModularTime.objectiveObserverViews[51]"},{"observerId":3785,"sourcePath":"observerModularTime.objectiveObserverViews[52]"},{"observerId":3933,"sourcePath":"observerModularTime.objectiveObserverViews[53]"},{"observerId":3951,"sourcePath":"observerModularTime.objectiveObserverViews[54]"},{"observerId":4195,"sourcePath":"observerModularTime.objectiveObserverViews[55]"},{"observerId":4238,"sourcePath":"observerModularTime.objectiveObserverViews[56]"},{"observerId":4260,"sourcePath":"observerModularTime.objectiveObserverViews[57]"},{"observerId":4279,"sourcePath":"observerModularTime.objectiveObserverViews[58]"},{"observerId":4300,"sourcePath":"observerModularTime.objectiveObserverViews[59]"},{"observerId":4314,"sourcePath":"observerModularTime.objectiveObserverViews[60]"},{"observerId":4333,"sourcePath":"observerModularTime.objectiveObserverViews[61]"},{"observerId":4365,"sourcePath":"observerModularTime.objectiveObserverViews[62]"},{"observerId":4399,"sourcePath":"observerModularTime.objectiveObserverViews[63]"},{"observerId":4407,"sourcePath":"observerModularTime.objectiveObserverViews[64]"},{"observerId":4516,"sourcePath":"observerModularTime.objectiveObserverViews[65]"},{"observerId":4539,"sourcePath":"observerModularTime.objectiveObserverViews[66]"},{"observerId":4593,"sourcePath":"observerModularTime.objectiveObserverViews[67]"},{"observerId":4655,"sourcePath":"observerModularTime.objectiveObserverViews[68]"},{"observerId":4747,"sourcePath":"observerModularTime.objectiveObserverViews[69]"},{"observerId":4754,"sourcePath":"observerModularTime.objectiveObserverViews[70]"},{"observerId":4783,"sourcePath":"observerModularTime.objectiveObserverViews[71]"},{"observerId":4977,"sourcePath":"observerModularTime.objectiveObserverViews[72]"},{"observerId":5149,"sourcePath":"observerModularTime.objectiveObserverViews[73]"},{"observerId":5154,"sourcePath":"observerModularTime.objectiveObserverViews[74]"},{"observerId":5214,"sourcePath":"observerModularTime.objectiveObserverViews[75]"},{"observerId":5281,"sourcePath":"observerModularTime.objectiveObserverViews[76]"},{"observerId":5406,"sourcePath":"observerModularTime.objectiveObserverViews[77]"},{"observerId":5417,"sourcePath":"observerModularTime.objectiveObserverViews[78]"},{"observerId":5432,"sourcePath":"observerModularTime.objectiveObserverViews[79]"},{"observerId":5454,"sourcePath":"observerModularTime.objectiveObserverViews[80]"},{"observerId":5468,"sourcePath":"observerModularTime.objectiveObserverViews[81]"},{"observerId":5663,"sourcePath":"observerModularTime.objectiveObserverViews[82]"},{"observerId":5713,"sourcePath":"observerModularTime.objectiveObserverViews[83]"},{"observerId":5744,"sourcePath":"observerModularTime.objectiveObserverViews[84]"},{"observerId":6173,"sourcePath":"observerModularTime.objectiveObserverViews[85]"},{"observerId":6193,"sourcePath":"observerModularTime.objectiveObserverViews[86]"},{"observerId":6195,"sourcePath":"observerModularTime.objectiveObserverViews[87]"},{"observerId":6266,"sourcePath":"observerModularTime.objectiveObserverViews[88]"},{"observerId":6342,"sourcePath":"observerModularTime.objectiveObserverViews[89]"},{"observerId":6344,"sourcePath":"observerModularTime.objectiveObserverViews[90]"},{"observerId":6452,"sourcePath":"observerModularTime.objectiveObserverViews[91]"},{"observerId":6474,"sourcePath":"observerModularTime.objectiveObserverViews[92]"},{"observerId":6476,"sourcePath":"observerModularTime.objectiveObserverViews[93]"},{"observerId":6505,"sourcePath":"observerModularTime.objectiveObserverViews[94]"},{"observerId":6581,"sourcePath":"observerModularTime.objectiveObserverViews[95]"},{"observerId":6675,"sourcePath":"observerModularTime.objectiveObserverViews[96]"},{"observerId":6806,"sourcePath":"observerModularTime.objectiveObserverViews[97]"},{"observerId":6818,"sourcePath":"observerModularTime.objectiveObserverViews[98]"},{"observerId":6840,"sourcePath":"observerModularTime.objectiveObserverViews[99]"},{"observerId":6881,"sourcePath":"observerModularTime.objectiveObserverViews[100]"},{"observerId":6972,"sourcePath":"observerModularTime.objectiveObserverViews[101]"},{"observerId":7003,"sourcePath":"observerModularTime.objectiveObserverViews[102]"},{"observerId":7081,"sourcePath":"observerModularTime.objectiveObserverViews[103]"},{"observerId":7148,"sourcePath":"observerModularTime.objectiveObserverViews[104]"},{"observerId":7216,"sourcePath":"observerModularTime.objectiveObserverViews[105]"},{"observerId":7233,"sourcePath":"observerModularTime.objectiveObserverViews[106]"},{"observerId":7257,"sourcePath":"observerModularTime.objectiveObserverViews[107]"},{"observerId":7304,"sourcePath":"observerModularTime.objectiveObserverViews[108]"},{"observerId":7326,"sourcePath":"observerModularTime.objectiveObserverViews[109]"},{"observerId":7480,"sourcePath":"observerModularTime.objectiveObserverViews[110]"},{"observerId":7612,"sourcePath":"observerModularTime.objectiveObserverViews[111]"},{"observerId":7655,"sourcePath":"observerModularTime.objectiveObserverViews[112]"},{"observerId":7813,"sourcePath":"observerModularTime.objectiveObserverViews[113]"},{"observerId":7874,"sourcePath":"observerModularTime.objectiveObserverViews[114]"},{"observerId":7964,"sourcePath":"observerModularTime.objectiveObserverViews[115]"},{"observerId":8061,"sourcePath":"observerModularTime.objectiveObserverViews[116]"},{"observerId":8075,"sourcePath":"observerModularTime.objectiveObserverViews[117]"},{"observerId":8277,"sourcePath":"observerModularTime.objectiveObserverViews[118]"},{"observerId":8286,"sourcePath":"observerModularTime.objectiveObserverViews[119]"},{"observerId":8337,"sourcePath":"observerModularTime.objectiveObserverViews[120]"},{"observerId":8570,"sourcePath":"observerModularTime.objectiveObserverViews[121]"},{"observerId":8629,"sourcePath":"observerModularTime.objectiveObserverViews[122]"},{"observerId":8785,"sourcePath":"observerModularTime.objectiveObserverViews[123]"},{"observerId":8807,"sourcePath":"observerModularTime.objectiveObserverViews[124]"},{"observerId":8852,"sourcePath":"observerModularTime.objectiveObserverViews[125]"},{"observerId":8888,"sourcePath":"observerModularTime.objectiveObserverViews[126]"},{"observerId":8989,"sourcePath":"observerModularTime.objectiveObserverViews[127]"}],"subjectiveCameraRefs":[{"cameraId":"subjective_observer_276","observerId":276,"sourcePath":"subjectiveObserverCameras[0]"},{"cameraId":"subjective_observer_503","observerId":503,"sourcePath":"subjectiveObserverCameras[1]"},{"cameraId":"subjective_observer_522","observerId":522,"sourcePath":"subjectiveObserverCameras[2]"},{"cameraId":"subjective_observer_535","observerId":535,"sourcePath":"subjectiveObserverCameras[3]"},{"cameraId":"subjective_observer_579","observerId":579,"sourcePath":"subjectiveObserverCameras[4]"},{"cameraId":"subjective_observer_609","observerId":609,"sourcePath":"subjectiveObserverCameras[5]"},{"cameraId":"subjective_observer_615","observerId":615,"sourcePath":"subjectiveObserverCameras[6]"},{"cameraId":"subjective_observer_631","observerId":631,"sourcePath":"subjectiveObserverCameras[7]"},{"cameraId":"subjective_observer_776","observerId":776,"sourcePath":"subjectiveObserverCameras[8]"},{"cameraId":"subjective_observer_841","observerId":841,"sourcePath":"subjectiveObserverCameras[9]"},{"cameraId":"subjective_observer_868","observerId":868,"sourcePath":"subjectiveObserverCameras[10]"},{"cameraId":"subjective_observer_1178","observerId":1178,"sourcePath":"subjectiveObserverCameras[11]"},{"cameraId":"subjective_observer_1282","observerId":1282,"sourcePath":"subjectiveObserverCameras[12]"},{"cameraId":"subjective_observer_1314","observerId":1314,"sourcePath":"subjectiveObserverCameras[13]"},{"cameraId":"subjective_observer_1395","observerId":1395,"sourcePath":"subjectiveObserverCameras[14]"},{"cameraId":"subjective_observer_1421","observerId":1421,"sourcePath":"subjectiveObserverCameras[15]"},{"cameraId":"subjective_observer_1558","observerId":1558,"sourcePath":"subjectiveObserverCameras[16]"},{"cameraId":"subjective_observer_1638","observerId":1638,"sourcePath":"subjectiveObserverCameras[17]"},{"cameraId":"subjective_observer_1648","observerId":1648,"sourcePath":"subjectiveObserverCameras[18]"},{"cameraId":"subjective_observer_1674","observerId":1674,"sourcePath":"subjectiveObserverCameras[19]"},{"cameraId":"subjective_observer_1705","observerId":1705,"sourcePath":"subjectiveObserverCameras[20]"},{"cameraId":"subjective_observer_1755","observerId":1755,"sourcePath":"subjectiveObserverCameras[21]"},{"cameraId":"subjective_observer_1814","observerId":1814,"sourcePath":"subjectiveObserverCameras[22]"},{"cameraId":"subjective_observer_1850","observerId":1850,"sourcePath":"subjectiveObserverCameras[23]"},{"cameraId":"subjective_observer_1852","observerId":1852,"sourcePath":"subjectiveObserverCameras[24]"},{"cameraId":"subjective_observer_1877","observerId":1877,"sourcePath":"subjectiveObserverCameras[25]"},{"cameraId":"subjective_observer_1987","observerId":1987,"sourcePath":"subjectiveObserverCameras[26]"},{"cameraId":"subjective_observer_2048","observerId":2048,"sourcePath":"subjectiveObserverCameras[27]"},{"cameraId":"subjective_observer_2123","observerId":2123,"sourcePath":"subjectiveObserverCameras[28]"},{"cameraId":"subjective_observer_2161","observerId":2161,"sourcePath":"subjectiveObserverCameras[29]"},{"cameraId":"subjective_observer_2170","observerId":2170,"sourcePath":"subjectiveObserverCameras[30]"},{"cameraId":"subjective_observer_2266","observerId":2266,"sourcePath":"subjectiveObserverCameras[31]"},{"cameraId":"subjective_observer_2341","observerId":2341,"sourcePath":"subjectiveObserverCameras[32]"},{"cameraId":"subjective_observer_2370","observerId":2370,"sourcePath":"subjectiveObserverCameras[33]"},{"cameraId":"subjective_observer_2410","observerId":2410,"sourcePath":"subjectiveObserverCameras[34]"},{"cameraId":"subjective_observer_2594","observerId":2594,"sourcePath":"subjectiveObserverCameras[35]"},{"cameraId":"subjective_observer_2596","observerId":2596,"sourcePath":"subjectiveObserverCameras[36]"},{"cameraId":"subjective_observer_2631","observerId":2631,"sourcePath":"subjectiveObserverCameras[37]"},{"cameraId":"subjective_observer_2673","observerId":2673,"sourcePath":"subjectiveObserverCameras[38]"},{"cameraId":"subjective_observer_2684","observerId":2684,"sourcePath":"subjectiveObserverCameras[39]"},{"cameraId":"subjective_observer_2728","observerId":2728,"sourcePath":"subjectiveObserverCameras[40]"},{"cameraId":"subjective_observer_2909","observerId":2909,"sourcePath":"subjectiveObserverCameras[41]"},{"cameraId":"subjective_observer_2937","observerId":2937,"sourcePath":"subjectiveObserverCameras[42]"},{"cameraId":"subjective_observer_3078","observerId":3078,"sourcePath":"subjectiveObserverCameras[43]"},{"cameraId":"subjective_observer_3155","observerId":3155,"sourcePath":"subjectiveObserverCameras[44]"},{"cameraId":"subjective_observer_3408","observerId":3408,"sourcePath":"subjectiveObserverCameras[45]"},{"cameraId":"subjective_observer_3432","observerId":3432,"sourcePath":"subjectiveObserverCameras[46]"},{"cameraId":"subjective_observer_3644","observerId":3644,"sourcePath":"subjectiveObserverCameras[47]"},{"cameraId":"subjective_observer_3731","observerId":3731,"sourcePath":"subjectiveObserverCameras[48]"},{"cameraId":"subjective_observer_3736","observerId":3736,"sourcePath":"subjectiveObserverCameras[49]"},{"cameraId":"subjective_observer_3771","observerId":3771,"sourcePath":"subjectiveObserverCameras[50]"},{"cameraId":"subjective_observer_3779","observerId":3779,"sourcePath":"subjectiveObserverCameras[51]"},{"cameraId":"subjective_observer_3785","observerId":3785,"sourcePath":"subjectiveObserverCameras[52]"},{"cameraId":"subjective_observer_3933","observerId":3933,"sourcePath":"subjectiveObserverCameras[53]"},{"cameraId":"subjective_observer_3951","observerId":3951,"sourcePath":"subjectiveObserverCameras[54]"},{"cameraId":"subjective_observer_4195","observerId":4195,"sourcePath":"subjectiveObserverCameras[55]"},{"cameraId":"subjective_observer_4238","observerId":4238,"sourcePath":"subjectiveObserverCameras[56]"},{"cameraId":"subjective_observer_4260","observerId":4260,"sourcePath":"subjectiveObserverCameras[57]"},{"cameraId":"subjective_observer_4279","observerId":4279,"sourcePath":"subjectiveObserverCameras[58]"},{"cameraId":"subjective_observer_4300","observerId":4300,"sourcePath":"subjectiveObserverCameras[59]"},{"cameraId":"subjective_observer_4314","observerId":4314,"sourcePath":"subjectiveObserverCameras[60]"},{"cameraId":"subjective_observer_4333","observerId":4333,"sourcePath":"subjectiveObserverCameras[61]"},{"cameraId":"subjective_observer_4365","observerId":4365,"sourcePath":"subjectiveObserverCameras[62]"},{"cameraId":"subjective_observer_4399","observerId":4399,"sourcePath":"subjectiveObserverCameras[63]"},{"cameraId":"subjective_observer_4407","observerId":4407,"sourcePath":"subjectiveObserverCameras[64]"},{"cameraId":"subjective_observer_4516","observerId":4516,"sourcePath":"subjectiveObserverCameras[65]"},{"cameraId":"subjective_observer_4539","observerId":4539,"sourcePath":"subjectiveObserverCameras[66]"},{"cameraId":"subjective_observer_4593","observerId":4593,"sourcePath":"subjectiveObserverCameras[67]"},{"cameraId":"subjective_observer_4655","observerId":4655,"sourcePath":"subjectiveObserverCameras[68]"},{"cameraId":"subjective_observer_4747","observerId":4747,"sourcePath":"subjectiveObserverCameras[69]"},{"cameraId":"subjective_observer_4754","observerId":4754,"sourcePath":"subjectiveObserverCameras[70]"},{"cameraId":"subjective_observer_4783","observerId":4783,"sourcePath":"subjectiveObserverCameras[71]"},{"cameraId":"subjective_observer_4977","observerId":4977,"sourcePath":"subjectiveObserverCameras[72]"},{"cameraId":"subjective_observer_5149","observerId":5149,"sourcePath":"subjectiveObserverCameras[73]"},{"cameraId":"subjective_observer_5154","observerId":5154,"sourcePath":"subjectiveObserverCameras[74]"},{"cameraId":"subjective_observer_5214","observerId":5214,"sourcePath":"subjectiveObserverCameras[75]"},{"cameraId":"subjective_observer_5281","observerId":5281,"sourcePath":"subjectiveObserverCameras[76]"},{"cameraId":"subjective_observer_5406","observerId":5406,"sourcePath":"subjectiveObserverCameras[77]"},{"cameraId":"subjective_observer_5417","observerId":5417,"sourcePath":"subjectiveObserverCameras[78]"},{"cameraId":"subjective_observer_5432","observerId":5432,"sourcePath":"subjectiveObserverCameras[79]"},{"cameraId":"subjective_observer_5454","observerId":5454,"sourcePath":"subjectiveObserverCameras[80]"},{"cameraId":"subjective_observer_5468","observerId":5468,"sourcePath":"subjectiveObserverCameras[81]"},{"cameraId":"subjective_observer_5663","observerId":5663,"sourcePath":"subjectiveObserverCameras[82]"},{"cameraId":"subjective_observer_5713","observerId":5713,"sourcePath":"subjectiveObserverCameras[83]"},{"cameraId":"subjective_observer_5744","observerId":5744,"sourcePath":"subjectiveObserverCameras[84]"},{"cameraId":"subjective_observer_6173","observerId":6173,"sourcePath":"subjectiveObserverCameras[85]"},{"cameraId":"subjective_observer_6193","observerId":6193,"sourcePath":"subjectiveObserverCameras[86]"},{"cameraId":"subjective_observer_6195","observerId":6195,"sourcePath":"subjectiveObserverCameras[87]"},{"cameraId":"subjective_observer_6266","observerId":6266,"sourcePath":"subjectiveObserverCameras[88]"},{"cameraId":"subjective_observer_6342","observerId":6342,"sourcePath":"subjectiveObserverCameras[89]"},{"cameraId":"subjective_observer_6344","observerId":6344,"sourcePath":"subjectiveObserverCameras[90]"},{"cameraId":"subjective_observer_6452","observerId":6452,"sourcePath":"subjectiveObserverCameras[91]"},{"cameraId":"subjective_observer_6474","observerId":6474,"sourcePath":"subjectiveObserverCameras[92]"},{"cameraId":"subjective_observer_6476","observerId":6476,"sourcePath":"subjectiveObserverCameras[93]"},{"cameraId":"subjective_observer_6505","observerId":6505,"sourcePath":"subjectiveObserverCameras[94]"},{"cameraId":"subjective_observer_6581","observerId":6581,"sourcePath":"subjectiveObserverCameras[95]"},{"cameraId":"subjective_observer_6675","observerId":6675,"sourcePath":"subjectiveObserverCameras[96]"},{"cameraId":"subjective_observer_6806","observerId":6806,"sourcePath":"subjectiveObserverCameras[97]"},{"cameraId":"subjective_observer_6818","observerId":6818,"sourcePath":"subjectiveObserverCameras[98]"},{"cameraId":"subjective_observer_6840","observerId":6840,"sourcePath":"subjectiveObserverCameras[99]"},{"cameraId":"subjective_observer_6881","observerId":6881,"sourcePath":"subjectiveObserverCameras[100]"},{"cameraId":"subjective_observer_6972","observerId":6972,"sourcePath":"subjectiveObserverCameras[101]"},{"cameraId":"subjective_observer_7003","observerId":7003,"sourcePath":"subjectiveObserverCameras[102]"},{"cameraId":"subjective_observer_7081","observerId":7081,"sourcePath":"subjectiveObserverCameras[103]"},{"cameraId":"subjective_observer_7148","observerId":7148,"sourcePath":"subjectiveObserverCameras[104]"},{"cameraId":"subjective_observer_7216","observerId":7216,"sourcePath":"subjectiveObserverCameras[105]"},{"cameraId":"subjective_observer_7233","observerId":7233,"sourcePath":"subjectiveObserverCameras[106]"},{"cameraId":"subjective_observer_7257","observerId":7257,"sourcePath":"subjectiveObserverCameras[107]"},{"cameraId":"subjective_observer_7304","observerId":7304,"sourcePath":"subjectiveObserverCameras[108]"},{"cameraId":"subjective_observer_7326","observerId":7326,"sourcePath":"subjectiveObserverCameras[109]"},{"cameraId":"subjective_observer_7480","observerId":7480,"sourcePath":"subjectiveObserverCameras[110]"},{"cameraId":"subjective_observer_7612","observerId":7612,"sourcePath":"subjectiveObserverCameras[111]"},{"cameraId":"subjective_observer_7655","observerId":7655,"sourcePath":"subjectiveObserverCameras[112]"},{"cameraId":"subjective_observer_7813","observerId":7813,"sourcePath":"subjectiveObserverCameras[113]"},{"cameraId":"subjective_observer_7874","observerId":7874,"sourcePath":"subjectiveObserverCameras[114]"},{"cameraId":"subjective_observer_7964","observerId":7964,"sourcePath":"subjectiveObserverCameras[115]"},{"cameraId":"subjective_observer_8061","observerId":8061,"sourcePath":"subjectiveObserverCameras[116]"},{"cameraId":"subjective_observer_8075","observerId":8075,"sourcePath":"subjectiveObserverCameras[117]"},{"cameraId":"subjective_observer_8277","observerId":8277,"sourcePath":"subjectiveObserverCameras[118]"},{"cameraId":"subjective_observer_8286","observerId":8286,"sourcePath":"subjectiveObserverCameras[119]"},{"cameraId":"subjective_observer_8337","observerId":8337,"sourcePath":"subjectiveObserverCameras[120]"},{"cameraId":"subjective_observer_8570","observerId":8570,"sourcePath":"subjectiveObserverCameras[121]"},{"cameraId":"subjective_observer_8629","observerId":8629,"sourcePath":"subjectiveObserverCameras[122]"},{"cameraId":"subjective_observer_8785","observerId":8785,"sourcePath":"subjectiveObserverCameras[123]"},{"cameraId":"subjective_observer_8807","observerId":8807,"sourcePath":"subjectiveObserverCameras[124]"},{"cameraId":"subjective_observer_8852","observerId":8852,"sourcePath":"subjectiveObserverCameras[125]"},{"cameraId":"subjective_observer_8888","observerId":8888,"sourcePath":"subjectiveObserverCameras[126]"},{"cameraId":"subjective_observer_8989","observerId":8989,"sourcePath":"subjectiveObserverCameras[127]"}],"globalTimelineFrameRefs":[{"relativeTime":0.0,"sourcePath":"observerModularTime.timeFrames[0]"},{"relativeTime":0.007874015748031496,"sourcePath":"observerModularTime.timeFrames[1]"},{"relativeTime":0.015748031496062992,"sourcePath":"observerModularTime.timeFrames[2]"},{"relativeTime":0.023622047244094488,"sourcePath":"observerModularTime.timeFrames[3]"},{"relativeTime":0.031496062992125984,"sourcePath":"observerModularTime.timeFrames[4]"},{"relativeTime":0.03937007874015748,"sourcePath":"observerModularTime.timeFrames[5]"},{"relativeTime":0.047244094488188976,"sourcePath":"observerModularTime.timeFrames[6]"},{"relativeTime":0.05511811023622047,"sourcePath":"observerModularTime.timeFrames[7]"},{"relativeTime":0.06299212598425197,"sourcePath":"observerModularTime.timeFrames[8]"},{"relativeTime":0.07086614173228346,"sourcePath":"observerModularTime.timeFrames[9]"},{"relativeTime":0.07874015748031496,"sourcePath":"observerModularTime.timeFrames[10]"},{"relativeTime":0.08661417322834646,"sourcePath":"observerModularTime.timeFrames[11]"},{"relativeTime":0.09448818897637795,"sourcePath":"observerModularTime.timeFrames[12]"},{"relativeTime":0.10236220472440945,"sourcePath":"observerModularTime.timeFrames[13]"},{"relativeTime":0.11023622047244094,"sourcePath":"observerModularTime.timeFrames[14]"},{"relativeTime":0.11811023622047244,"sourcePath":"observerModularTime.timeFrames[15]"},{"relativeTime":0.12598425196850394,"sourcePath":"observerModularTime.timeFrames[16]"},{"relativeTime":0.13385826771653545,"sourcePath":"observerModularTime.timeFrames[17]"},{"relativeTime":0.14173228346456693,"sourcePath":"observerModularTime.timeFrames[18]"},{"relativeTime":0.14960629921259844,"sourcePath":"observerModularTime.timeFrames[19]"},{"relativeTime":0.15748031496062992,"sourcePath":"observerModularTime.timeFrames[20]"},{"relativeTime":0.16535433070866143,"sourcePath":"observerModularTime.timeFrames[21]"},{"relativeTime":0.1732283464566929,"sourcePath":"observerModularTime.timeFrames[22]"},{"relativeTime":0.18110236220472442,"sourcePath":"observerModularTime.timeFrames[23]"},{"relativeTime":0.1889763779527559,"sourcePath":"observerModularTime.timeFrames[24]"},{"relativeTime":0.1968503937007874,"sourcePath":"observerModularTime.timeFrames[25]"},{"relativeTime":0.2047244094488189,"sourcePath":"observerModularTime.timeFrames[26]"},{"relativeTime":0.2125984251968504,"sourcePath":"observerModularTime.timeFrames[27]"},{"relativeTime":0.2204724409448819,"sourcePath":"observerModularTime.timeFrames[28]"},{"relativeTime":0.2283464566929134,"sourcePath":"observerModularTime.timeFrames[29]"},{"relativeTime":0.23622047244094488,"sourcePath":"observerModularTime.timeFrames[30]"},{"relativeTime":0.2440944881889764,"sourcePath":"observerModularTime.timeFrames[31]"},{"relativeTime":0.25196850393700787,"sourcePath":"observerModularTime.timeFrames[32]"},{"relativeTime":0.25984251968503935,"sourcePath":"observerModularTime.timeFrames[33]"},{"relativeTime":0.2677165354330709,"sourcePath":"observerModularTime.timeFrames[34]"},{"relativeTime":0.2755905511811024,"sourcePath":"observerModularTime.timeFrames[35]"},{"relativeTime":0.28346456692913385,"sourcePath":"observerModularTime.timeFrames[36]"},{"relativeTime":0.29133858267716534,"sourcePath":"observerModularTime.timeFrames[37]"},{"relativeTime":0.2992125984251969,"sourcePath":"observerModularTime.timeFrames[38]"},{"relativeTime":0.30708661417322836,"sourcePath":"observerModularTime.timeFrames[39]"},{"relativeTime":0.31496062992125984,"sourcePath":"observerModularTime.timeFrames[40]"},{"relativeTime":0.3228346456692913,"sourcePath":"observerModularTime.timeFrames[41]"},{"relativeTime":0.33070866141732286,"sourcePath":"observerModularTime.timeFrames[42]"},{"relativeTime":0.33858267716535434,"sourcePath":"observerModularTime.timeFrames[43]"},{"relativeTime":0.3464566929133858,"sourcePath":"observerModularTime.timeFrames[44]"},{"relativeTime":0.3543307086614173,"sourcePath":"observerModularTime.timeFrames[45]"},{"relativeTime":0.36220472440944884,"sourcePath":"observerModularTime.timeFrames[46]"},{"relativeTime":0.3700787401574803,"sourcePath":"observerModularTime.timeFrames[47]"},{"relativeTime":0.3779527559055118,"sourcePath":"observerModularTime.timeFrames[48]"},{"relativeTime":0.3858267716535433,"sourcePath":"observerModularTime.timeFrames[49]"},{"relativeTime":0.3937007874015748,"sourcePath":"observerModularTime.timeFrames[50]"},{"relativeTime":0.4015748031496063,"sourcePath":"observerModularTime.timeFrames[51]"},{"relativeTime":0.4094488188976378,"sourcePath":"observerModularTime.timeFrames[52]"},{"relativeTime":0.41732283464566927,"sourcePath":"observerModularTime.timeFrames[53]"},{"relativeTime":0.4251968503937008,"sourcePath":"observerModularTime.timeFrames[54]"},{"relativeTime":0.4330708661417323,"sourcePath":"observerModularTime.timeFrames[55]"},{"relativeTime":0.4409448818897638,"sourcePath":"observerModularTime.timeFrames[56]"},{"relativeTime":0.44881889763779526,"sourcePath":"observerModularTime.timeFrames[57]"},{"relativeTime":0.4566929133858268,"sourcePath":"observerModularTime.timeFrames[58]"},{"relativeTime":0.4645669291338583,"sourcePath":"observerModularTime.timeFrames[59]"},{"relativeTime":0.47244094488188976,"sourcePath":"observerModularTime.timeFrames[60]"},{"relativeTime":0.48031496062992124,"sourcePath":"observerModularTime.timeFrames[61]"},{"relativeTime":0.4881889763779528,"sourcePath":"observerModularTime.timeFrames[62]"},{"relativeTime":0.49606299212598426,"sourcePath":"observerModularTime.timeFrames[63]"},{"relativeTime":0.5039370078740157,"sourcePath":"observerModularTime.timeFrames[64]"},{"relativeTime":0.5118110236220472,"sourcePath":"observerModularTime.timeFrames[65]"},{"relativeTime":0.5196850393700787,"sourcePath":"observerModularTime.timeFrames[66]"},{"relativeTime":0.5275590551181102,"sourcePath":"observerModularTime.timeFrames[67]"},{"relativeTime":0.5354330708661418,"sourcePath":"observerModularTime.timeFrames[68]"},{"relativeTime":0.5433070866141733,"sourcePath":"observerModularTime.timeFrames[69]"},{"relativeTime":0.5511811023622047,"sourcePath":"observerModularTime.timeFrames[70]"},{"relativeTime":0.5590551181102362,"sourcePath":"observerModularTime.timeFrames[71]"},{"relativeTime":0.5669291338582677,"sourcePath":"observerModularTime.timeFrames[72]"},{"relativeTime":0.5748031496062992,"sourcePath":"observerModularTime.timeFrames[73]"},{"relativeTime":0.5826771653543307,"sourcePath":"observerModularTime.timeFrames[74]"},{"relativeTime":0.5905511811023622,"sourcePath":"observerModularTime.timeFrames[75]"},{"relativeTime":0.5984251968503937,"sourcePath":"observerModularTime.timeFrames[76]"},{"relativeTime":0.6062992125984252,"sourcePath":"observerModularTime.timeFrames[77]"},{"relativeTime":0.6141732283464567,"sourcePath":"observerModularTime.timeFrames[78]"},{"relativeTime":0.6220472440944882,"sourcePath":"observerModularTime.timeFrames[79]"},{"relativeTime":0.6299212598425197,"sourcePath":"observerModularTime.timeFrames[80]"},{"relativeTime":0.6377952755905512,"sourcePath":"observerModularTime.timeFrames[81]"},{"relativeTime":0.6456692913385826,"sourcePath":"observerModularTime.timeFrames[82]"},{"relativeTime":0.6535433070866141,"sourcePath":"observerModularTime.timeFrames[83]"},{"relativeTime":0.6614173228346457,"sourcePath":"observerModularTime.timeFrames[84]"},{"relativeTime":0.6692913385826772,"sourcePath":"observerModularTime.timeFrames[85]"},{"relativeTime":0.6771653543307087,"sourcePath":"observerModularTime.timeFrames[86]"},{"relativeTime":0.6850393700787402,"sourcePath":"observerModularTime.timeFrames[87]"},{"relativeTime":0.6929133858267716,"sourcePath":"observerModularTime.timeFrames[88]"},{"relativeTime":0.7007874015748031,"sourcePath":"observerModularTime.timeFrames[89]"},{"relativeTime":0.7086614173228346,"sourcePath":"observerModularTime.timeFrames[90]"},{"relativeTime":0.7165354330708661,"sourcePath":"observerModularTime.timeFrames[91]"},{"relativeTime":0.7244094488188977,"sourcePath":"observerModularTime.timeFrames[92]"},{"relativeTime":0.7322834645669292,"sourcePath":"observerModularTime.timeFrames[93]"},{"relativeTime":0.7401574803149606,"sourcePath":"observerModularTime.timeFrames[94]"},{"relativeTime":0.7480314960629921,"sourcePath":"observerModularTime.timeFrames[95]"},{"relativeTime":0.7559055118110236,"sourcePath":"observerModularTime.timeFrames[96]"},{"relativeTime":0.7637795275590551,"sourcePath":"observerModularTime.timeFrames[97]"},{"relativeTime":0.7716535433070866,"sourcePath":"observerModularTime.timeFrames[98]"},{"relativeTime":0.7795275590551181,"sourcePath":"observerModularTime.timeFrames[99]"},{"relativeTime":0.7874015748031497,"sourcePath":"observerModularTime.timeFrames[100]"},{"relativeTime":0.7952755905511811,"sourcePath":"observerModularTime.timeFrames[101]"},{"relativeTime":0.8031496062992126,"sourcePath":"observerModularTime.timeFrames[102]"},{"relativeTime":0.8110236220472441,"sourcePath":"observerModularTime.timeFrames[103]"},{"relativeTime":0.8188976377952756,"sourcePath":"observerModularTime.timeFrames[104]"},{"relativeTime":0.8267716535433071,"sourcePath":"observerModularTime.timeFrames[105]"},{"relativeTime":0.8346456692913385,"sourcePath":"observerModularTime.timeFrames[106]"},{"relativeTime":0.84251968503937,"sourcePath":"observerModularTime.timeFrames[107]"},{"relativeTime":0.8503937007874016,"sourcePath":"observerModularTime.timeFrames[108]"},{"relativeTime":0.8582677165354331,"sourcePath":"observerModularTime.timeFrames[109]"},{"relativeTime":0.8661417322834646,"sourcePath":"observerModularTime.timeFrames[110]"},{"relativeTime":0.8740157480314961,"sourcePath":"observerModularTime.timeFrames[111]"},{"relativeTime":0.8818897637795275,"sourcePath":"observerModularTime.timeFrames[112]"},{"relativeTime":0.889763779527559,"sourcePath":"observerModularTime.timeFrames[113]"},{"relativeTime":0.8976377952755905,"sourcePath":"observerModularTime.timeFrames[114]"},{"relativeTime":0.905511811023622,"sourcePath":"observerModularTime.timeFrames[115]"},{"relativeTime":0.9133858267716536,"sourcePath":"observerModularTime.timeFrames[116]"},{"relativeTime":0.9212598425196851,"sourcePath":"observerModularTime.timeFrames[117]"},{"relativeTime":0.9291338582677166,"sourcePath":"observerModularTime.timeFrames[118]"},{"relativeTime":0.937007874015748,"sourcePath":"observerModularTime.timeFrames[119]"},{"relativeTime":0.9448818897637795,"sourcePath":"observerModularTime.timeFrames[120]"},{"relativeTime":0.952755905511811,"sourcePath":"observerModularTime.timeFrames[121]"},{"relativeTime":0.9606299212598425,"sourcePath":"observerModularTime.timeFrames[122]"},{"relativeTime":0.968503937007874,"sourcePath":"observerModularTime.timeFrames[123]"},{"relativeTime":0.9763779527559056,"sourcePath":"observerModularTime.timeFrames[124]"},{"relativeTime":0.984251968503937,"sourcePath":"observerModularTime.timeFrames[125]"},{"relativeTime":0.9921259842519685,"sourcePath":"observerModularTime.timeFrames[126]"},{"relativeTime":1.0,"sourcePath":"observerModularTime.timeFrames[127]"}],"overlapLinkRefs":[{"linkId":null,"sourcePath":"observerModularTime.overlapLinks[0]"},{"linkId":null,"sourcePath":"observerModularTime.overlapLinks[1]"},{"linkId":null,"sourcePath":"observerModularTime.overlapLinks[2]"},{"linkId":null,"sourcePath":"observerModularTime.overlapLinks[3]"},{"linkId":null,"sourcePath":"observerModularTime.overlapLinks[4]"},{"linkId":null,"sourcePath":"observerModularTime.overlapLinks[5]"},{"linkId":null,"sourcePath":"observerModularTime.overlapLinks[6]"},{"linkId":null,"sourcePath":"observerModularTime.overlapLinks[7]"},{"linkId":null,"sourcePath":"observerModularTime.overlapLinks[8]"},{"linkId":null,"sourcePath":"observerModularTime.overlapLinks[9]"},{"linkId":null,"sourcePath":"observerModularTime.overlapLinks[10]"},{"linkId":null,"sourcePath":"observerModularTime.overlapLinks[11]"},{"linkId":null,"sourcePath":"observerModularTime.overlapLinks[12]"},{"linkId":null,"sourcePath":"observerModularTime.overlapLinks[13]"},{"linkId":null,"sourcePath":"observerModularTime.overlapLinks[14]"},{"linkId":null,"sourcePath":"observerModularTime.overlapLinks[15]"},{"linkId":null,"sourcePath":"observerModularTime.overlapLinks[16]"},{"linkId":null,"sourcePath":"observerModularTime.overlapLinks[17]"},{"linkId":null,"sourcePath":"observerModularTime.overlapLinks[18]"},{"linkId":null,"sourcePath":"observerModularTime.overlapLinks[19]"},{"linkId":null,"sourcePath":"observerModularTime.overlapLinks[20]"},{"linkId":null,"sourcePath":"observerModularTime.overlapLinks[21]"},{"linkId":null,"sourcePath":"observerModularTime.overlapLinks[22]"},{"linkId":null,"sourcePath":"observerModularTime.overlapLinks[23]"},{"linkId":null,"sourcePath":"observerModularTime.overlapLinks[24]"},{"linkId":null,"sourcePath":"observerModularTime.overlapLinks[25]"},{"linkId":null,"sourcePath":"observerModularTime.overlapLinks[26]"},{"linkId":null,"sourcePath":"observerModularTime.overlapLinks[27]"},{"linkId":null,"sourcePath":"observerModularTime.overlapLinks[28]"},{"linkId":null,"sourcePath":"observerModularTime.overlapLinks[29]"},{"linkId":null,"sourcePath":"observerModularTime.overlapLinks[30]"},{"linkId":null,"sourcePath":"observerModularTime.overlapLinks[31]"},{"linkId":null,"sourcePath":"observerModularTime.overlapLinks[32]"},{"linkId":null,"sourcePath":"observerModularTime.overlapLinks[33]"},{"linkId":null,"sourcePath":"observerModularTime.overlapLinks[34]"},{"linkId":null,"sourcePath":"observerModularTime.overlapLinks[35]"},{"linkId":null,"sourcePath":"observerModularTime.overlapLinks[36]"},{"linkId":null,"sourcePath":"observerModularTime.overlapLinks[37]"},{"linkId":null,"sourcePath":"observerModularTime.overlapLinks[38]"},{"linkId":null,"sourcePath":"observerModularTime.overlapLinks[39]"},{"linkId":null,"sourcePath":"observerModularTime.overlapLinks[40]"},{"linkId":null,"sourcePath":"observerModularTime.overlapLinks[41]"},{"linkId":null,"sourcePath":"observerModularTime.overlapLinks[42]"},{"linkId":null,"sourcePath":"observerModularTime.overlapLinks[43]"},{"linkId":null,"sourcePath":"observerModularTime.overlapLinks[44]"},{"linkId":null,"sourcePath":"observerModularTime.overlapLinks[45]"},{"linkId":null,"sourcePath":"observerModularTime.overlapLinks[46]"},{"linkId":null,"sourcePath":"observerModularTime.overlapLinks[47]"},{"linkId":null,"sourcePath":"observerModularTime.overlapLinks[48]"},{"linkId":null,"sourcePath":"observerModularTime.overlapLinks[49]"},{"linkId":null,"sourcePath":"observerModularTime.overlapLinks[50]"},{"linkId":null,"sourcePath":"observerModularTime.overlapLinks[51]"},{"linkId":null,"sourcePath":"observerModularTime.overlapLinks[52]"},{"linkId":null,"sourcePath":"observerModularTime.overlapLinks[53]"},{"linkId":null,"sourcePath":"observerModularTime.overlapLinks[54]"},{"linkId":null,"sourcePath":"observerModularTime.overlapLinks[55]"},{"linkId":null,"sourcePath":"observerModularTime.overlapLinks[56]"},{"linkId":null,"sourcePath":"observerModularTime.overlapLinks[57]"},{"linkId":null,"sourcePath":"observerModularTime.overlapLinks[58]"},{"linkId":null,"sourcePath":"observerModularTime.overlapLinks[59]"},{"linkId":null,"sourcePath":"observerModularTime.overlapLinks[60]"},{"linkId":null,"sourcePath":"observerModularTime.overlapLinks[61]"},{"linkId":null,"sourcePath":"observerModularTime.overlapLinks[62]"},{"linkId":null,"sourcePath":"observerModularTime.overlapLinks[63]"},{"linkId":null,"sourcePath":"observerModularTime.overlapLinks[64]"},{"linkId":null,"sourcePath":"observerModularTime.overlapLinks[65]"},{"linkId":null,"sourcePath":"observerModularTime.overlapLinks[66]"},{"linkId":null,"sourcePath":"observerModularTime.overlapLinks[67]"},{"linkId":null,"sourcePath":"observerModularTime.overlapLinks[68]"},{"linkId":null,"sourcePath":"observerModularTime.overlapLinks[69]"},{"linkId":null,"sourcePath":"observerModularTime.overlapLinks[70]"},{"linkId":null,"sourcePath":"observerModularTime.overlapLinks[71]"},{"linkId":null,"sourcePath":"observerModularTime.overlapLinks[72]"},{"linkId":null,"sourcePath":"observerModularTime.overlapLinks[73]"},{"linkId":null,"sourcePath":"observerModularTime.overlapLinks[74]"},{"linkId":null,"sourcePath":"observerModularTime.overlapLinks[75]"},{"linkId":null,"sourcePath":"observerModularTime.overlapLinks[76]"},{"linkId":null,"sourcePath":"observerModularTime.overlapLinks[77]"},{"linkId":null,"sourcePath":"observerModularTime.overlapLinks[78]"},{"linkId":null,"sourcePath":"observerModularTime.overlapLinks[79]"},{"linkId":null,"sourcePath":"observerModularTime.overlapLinks[80]"},{"linkId":null,"sourcePath":"observerModularTime.overlapLinks[81]"},{"linkId":null,"sourcePath":"observerModularTime.overlapLinks[82]"},{"linkId":null,"sourcePath":"observerModularTime.overlapLinks[83]"},{"linkId":null,"sourcePath":"observerModularTime.overlapLinks[84]"},{"linkId":null,"sourcePath":"observerModularTime.overlapLinks[85]"},{"linkId":null,"sourcePath":"observerModularTime.overlapLinks[86]"},{"linkId":null,"sourcePath":"observerModularTime.overlapLinks[87]"},{"linkId":null,"sourcePath":"observerModularTime.overlapLinks[88]"},{"linkId":null,"sourcePath":"observerModularTime.overlapLinks[89]"},{"linkId":null,"sourcePath":"observerModularTime.overlapLinks[90]"},{"linkId":null,"sourcePath":"observerModularTime.overlapLinks[91]"},{"linkId":null,"sourcePath":"observerModularTime.overlapLinks[92]"},{"linkId":null,"sourcePath":"observerModularTime.overlapLinks[93]"},{"linkId":null,"sourcePath":"observerModularTime.overlapLinks[94]"},{"linkId":null,"sourcePath":"observerModularTime.overlapLinks[95]"},{"linkId":null,"sourcePath":"observerModularTime.overlapLinks[96]"},{"linkId":null,"sourcePath":"observerModularTime.overlapLinks[97]"},{"linkId":null,"sourcePath":"observerModularTime.overlapLinks[98]"},{"linkId":null,"sourcePath":"observerModularTime.overlapLinks[99]"},{"linkId":null,"sourcePath":"observerModularTime.overlapLinks[100]"},{"linkId":null,"sourcePath":"observerModularTime.overlapLinks[101]"},{"linkId":null,"sourcePath":"observerModularTime.overlapLinks[102]"},{"linkId":null,"sourcePath":"observerModularTime.overlapLinks[103]"},{"linkId":null,"sourcePath":"observerModularTime.overlapLinks[104]"},{"linkId":null,"sourcePath":"observerModularTime.overlapLinks[105]"},{"linkId":null,"sourcePath":"observerModularTime.overlapLinks[106]"},{"linkId":null,"sourcePath":"observerModularTime.overlapLinks[107]"},{"linkId":null,"sourcePath":"observerModularTime.overlapLinks[108]"},{"linkId":null,"sourcePath":"observerModularTime.overlapLinks[109]"},{"linkId":null,"sourcePath":"observerModularTime.overlapLinks[110]"},{"linkId":null,"sourcePath":"observerModularTime.overlapLinks[111]"},{"linkId":null,"sourcePath":"observerModularTime.overlapLinks[112]"},{"linkId":null,"sourcePath":"observerModularTime.overlapLinks[113]"},{"linkId":null,"sourcePath":"observerModularTime.overlapLinks[114]"},{"linkId":null,"sourcePath":"observerModularTime.overlapLinks[115]"},{"linkId":null,"sourcePath":"observerModularTime.overlapLinks[116]"},{"linkId":null,"sourcePath":"observerModularTime.overlapLinks[117]"},{"linkId":null,"sourcePath":"observerModularTime.overlapLinks[118]"},{"linkId":null,"sourcePath":"observerModularTime.overlapLinks[119]"},{"linkId":null,"sourcePath":"observerModularTime.overlapLinks[120]"},{"linkId":null,"sourcePath":"observerModularTime.overlapLinks[121]"},{"linkId":null,"sourcePath":"observerModularTime.overlapLinks[122]"},{"linkId":null,"sourcePath":"observerModularTime.overlapLinks[123]"},{"linkId":null,"sourcePath":"observerModularTime.overlapLinks[124]"},{"linkId":null,"sourcePath":"observerModularTime.overlapLinks[125]"},{"linkId":null,"sourcePath":"observerModularTime.overlapLinks[126]"},{"linkId":null,"sourcePath":"observerModularTime.overlapLinks[127]"},{"linkId":null,"sourcePath":"observerModularTime.overlapLinks[128]"},{"linkId":null,"sourcePath":"observerModularTime.overlapLinks[129]"},{"linkId":null,"sourcePath":"observerModularTime.overlapLinks[130]"},{"linkId":null,"sourcePath":"observerModularTime.overlapLinks[131]"},{"linkId":null,"sourcePath":"observerModularTime.overlapLinks[132]"},{"linkId":null,"sourcePath":"observerModularTime.overlapLinks[133]"},{"linkId":null,"sourcePath":"observerModularTime.overlapLinks[134]"},{"linkId":null,"sourcePath":"observerModularTime.overlapLinks[135]"},{"linkId":null,"sourcePath":"observerModularTime.overlapLinks[136]"},{"linkId":null,"sourcePath":"observerModularTime.overlapLinks[137]"},{"linkId":null,"sourcePath":"observerModularTime.overlapLinks[138]"},{"linkId":null,"sourcePath":"observerModularTime.overlapLinks[139]"},{"linkId":null,"sourcePath":"observerModularTime.overlapLinks[140]"},{"linkId":null,"sourcePath":"observerModularTime.overlapLinks[141]"},{"linkId":null,"sourcePath":"observerModularTime.overlapLinks[142]"},{"linkId":null,"sourcePath":"observerModularTime.overlapLinks[143]"},{"linkId":null,"sourcePath":"observerModularTime.overlapLinks[144]"},{"linkId":null,"sourcePath":"observerModularTime.overlapLinks[145]"},{"linkId":null,"sourcePath":"observerModularTime.overlapLinks[146]"},{"linkId":null,"sourcePath":"observerModularTime.overlapLinks[147]"},{"linkId":null,"sourcePath":"observerModularTime.overlapLinks[148]"},{"linkId":null,"sourcePath":"observerModularTime.overlapLinks[149]"},{"linkId":null,"sourcePath":"observerModularTime.overlapLinks[150]"},{"linkId":null,"sourcePath":"observerModularTime.overlapLinks[151]"},{"linkId":null,"sourcePath":"observerModularTime.overlapLinks[152]"},{"linkId":null,"sourcePath":"observerModularTime.overlapLinks[153]"},{"linkId":null,"sourcePath":"observerModularTime.overlapLinks[154]"},{"linkId":null,"sourcePath":"observerModularTime.overlapLinks[155]"},{"linkId":null,"sourcePath":"observerModularTime.overlapLinks[156]"},{"linkId":null,"sourcePath":"observerModularTime.overlapLinks[157]"},{"linkId":null,"sourcePath":"observerModularTime.overlapLinks[158]"},{"linkId":null,"sourcePath":"observerModularTime.overlapLinks[159]"},{"linkId":null,"sourcePath":"observerModularTime.overlapLinks[160]"},{"linkId":null,"sourcePath":"observerModularTime.overlapLinks[161]"},{"linkId":null,"sourcePath":"observerModularTime.overlapLinks[162]"},{"linkId":null,"sourcePath":"observerModularTime.overlapLinks[163]"},{"linkId":null,"sourcePath":"observerModularTime.overlapLinks[164]"},{"linkId":null,"sourcePath":"observerModularTime.overlapLinks[165]"},{"linkId":null,"sourcePath":"observerModularTime.overlapLinks[166]"},{"linkId":null,"sourcePath":"observerModularTime.overlapLinks[167]"},{"linkId":null,"sourcePath":"observerModularTime.overlapLinks[168]"},{"linkId":null,"sourcePath":"observerModularTime.overlapLinks[169]"},{"linkId":null,"sourcePath":"observerModularTime.overlapLinks[170]"},{"linkId":null,"sourcePath":"observerModularTime.overlapLinks[171]"},{"linkId":null,"sourcePath":"observerModularTime.overlapLinks[172]"},{"linkId":null,"sourcePath":"observerModularTime.overlapLinks[173]"},{"linkId":null,"sourcePath":"observerModularTime.overlapLinks[174]"},{"linkId":null,"sourcePath":"observerModularTime.overlapLinks[175]"},{"linkId":null,"sourcePath":"observerModularTime.overlapLinks[176]"},{"linkId":null,"sourcePath":"observerModularTime.overlapLinks[177]"},{"linkId":null,"sourcePath":"observerModularTime.overlapLinks[178]"},{"linkId":null,"sourcePath":"observerModularTime.overlapLinks[179]"},{"linkId":null,"sourcePath":"observerModularTime.overlapLinks[180]"},{"linkId":null,"sourcePath":"observerModularTime.overlapLinks[181]"},{"linkId":null,"sourcePath":"observerModularTime.overlapLinks[182]"},{"linkId":null,"sourcePath":"observerModularTime.overlapLinks[183]"},{"linkId":null,"sourcePath":"observerModularTime.overlapLinks[184]"},{"linkId":null,"sourcePath":"observerModularTime.overlapLinks[185]"},{"linkId":null,"sourcePath":"observerModularTime.overlapLinks[186]"},{"linkId":null,"sourcePath":"observerModularTime.overlapLinks[187]"},{"linkId":null,"sourcePath":"observerModularTime.overlapLinks[188]"},{"linkId":null,"sourcePath":"observerModularTime.overlapLinks[189]"},{"linkId":null,"sourcePath":"observerModularTime.overlapLinks[190]"},{"linkId":null,"sourcePath":"observerModularTime.overlapLinks[191]"},{"linkId":null,"sourcePath":"observerModularTime.overlapLinks[192]"},{"linkId":null,"sourcePath":"observerModularTime.overlapLinks[193]"},{"linkId":null,"sourcePath":"observerModularTime.overlapLinks[194]"},{"linkId":null,"sourcePath":"observerModularTime.overlapLinks[195]"},{"linkId":null,"sourcePath":"observerModularTime.overlapLinks[196]"},{"linkId":null,"sourcePath":"observerModularTime.overlapLinks[197]"},{"linkId":null,"sourcePath":"observerModularTime.overlapLinks[198]"},{"linkId":null,"sourcePath":"observerModularTime.overlapLinks[199]"},{"linkId":null,"sourcePath":"observerModularTime.overlapLinks[200]"},{"linkId":null,"sourcePath":"observerModularTime.overlapLinks[201]"},{"linkId":null,"sourcePath":"observerModularTime.overlapLinks[202]"},{"linkId":null,"sourcePath":"observerModularTime.overlapLinks[203]"},{"linkId":null,"sourcePath":"observerModularTime.overlapLinks[204]"},{"linkId":null,"sourcePath":"observerModularTime.overlapLinks[205]"},{"linkId":null,"sourcePath":"observerModularTime.overlapLinks[206]"},{"linkId":null,"sourcePath":"observerModularTime.overlapLinks[207]"},{"linkId":null,"sourcePath":"observerModularTime.overlapLinks[208]"},{"linkId":null,"sourcePath":"observerModularTime.overlapLinks[209]"},{"linkId":null,"sourcePath":"observerModularTime.overlapLinks[210]"},{"linkId":null,"sourcePath":"observerModularTime.overlapLinks[211]"},{"linkId":null,"sourcePath":"observerModularTime.overlapLinks[212]"},{"linkId":null,"sourcePath":"observerModularTime.overlapLinks[213]"},{"linkId":null,"sourcePath":"observerModularTime.overlapLinks[214]"},{"linkId":null,"sourcePath":"observerModularTime.overlapLinks[215]"},{"linkId":null,"sourcePath":"observerModularTime.overlapLinks[216]"},{"linkId":null,"sourcePath":"observerModularTime.overlapLinks[217]"},{"linkId":null,"sourcePath":"observerModularTime.overlapLinks[218]"},{"linkId":null,"sourcePath":"observerModularTime.overlapLinks[219]"},{"linkId":null,"sourcePath":"observerModularTime.overlapLinks[220]"},{"linkId":null,"sourcePath":"observerModularTime.overlapLinks[221]"},{"linkId":null,"sourcePath":"observerModularTime.overlapLinks[222]"},{"linkId":null,"sourcePath":"observerModularTime.overlapLinks[223]"},{"linkId":null,"sourcePath":"observerModularTime.overlapLinks[224]"},{"linkId":null,"sourcePath":"observerModularTime.overlapLinks[225]"},{"linkId":null,"sourcePath":"observerModularTime.overlapLinks[226]"},{"linkId":null,"sourcePath":"observerModularTime.overlapLinks[227]"},{"linkId":null,"sourcePath":"observerModularTime.overlapLinks[228]"},{"linkId":null,"sourcePath":"observerModularTime.overlapLinks[229]"},{"linkId":null,"sourcePath":"observerModularTime.overlapLinks[230]"},{"linkId":null,"sourcePath":"observerModularTime.overlapLinks[231]"},{"linkId":null,"sourcePath":"observerModularTime.overlapLinks[232]"},{"linkId":null,"sourcePath":"observerModularTime.overlapLinks[233]"},{"linkId":null,"sourcePath":"observerModularTime.overlapLinks[234]"},{"linkId":null,"sourcePath":"observerModularTime.overlapLinks[235]"},{"linkId":null,"sourcePath":"observerModularTime.overlapLinks[236]"},{"linkId":null,"sourcePath":"observerModularTime.overlapLinks[237]"},{"linkId":null,"sourcePath":"observerModularTime.overlapLinks[238]"},{"linkId":null,"sourcePath":"observerModularTime.overlapLinks[239]"},{"linkId":null,"sourcePath":"observerModularTime.overlapLinks[240]"},{"linkId":null,"sourcePath":"observerModularTime.overlapLinks[241]"},{"linkId":null,"sourcePath":"observerModularTime.overlapLinks[242]"},{"linkId":null,"sourcePath":"observerModularTime.overlapLinks[243]"},{"linkId":null,"sourcePath":"observerModularTime.overlapLinks[244]"},{"linkId":null,"sourcePath":"observerModularTime.overlapLinks[245]"},{"linkId":null,"sourcePath":"observerModularTime.overlapLinks[246]"},{"linkId":null,"sourcePath":"observerModularTime.overlapLinks[247]"},{"linkId":null,"sourcePath":"observerModularTime.overlapLinks[248]"},{"linkId":null,"sourcePath":"observerModularTime.overlapLinks[249]"},{"linkId":null,"sourcePath":"observerModularTime.overlapLinks[250]"},{"linkId":null,"sourcePath":"observerModularTime.overlapLinks[251]"},{"linkId":null,"sourcePath":"observerModularTime.overlapLinks[252]"},{"linkId":null,"sourcePath":"observerModularTime.overlapLinks[253]"},{"linkId":null,"sourcePath":"observerModularTime.overlapLinks[254]"},{"linkId":null,"sourcePath":"observerModularTime.overlapLinks[255]"},{"linkId":null,"sourcePath":"observerModularTime.overlapLinks[256]"},{"linkId":null,"sourcePath":"observerModularTime.overlapLinks[257]"},{"linkId":null,"sourcePath":"observerModularTime.overlapLinks[258]"},{"linkId":null,"sourcePath":"observerModularTime.overlapLinks[259]"},{"linkId":null,"sourcePath":"observerModularTime.overlapLinks[260]"},{"linkId":null,"sourcePath":"observerModularTime.overlapLinks[261]"},{"linkId":null,"sourcePath":"observerModularTime.overlapLinks[262]"},{"linkId":null,"sourcePath":"observerModularTime.overlapLinks[263]"},{"linkId":null,"sourcePath":"observerModularTime.overlapLinks[264]"},{"linkId":null,"sourcePath":"observerModularTime.overlapLinks[265]"},{"linkId":null,"sourcePath":"observerModularTime.overlapLinks[266]"},{"linkId":null,"sourcePath":"observerModularTime.overlapLinks[267]"},{"linkId":null,"sourcePath":"observerModularTime.overlapLinks[268]"},{"linkId":null,"sourcePath":"observerModularTime.overlapLinks[269]"},{"linkId":null,"sourcePath":"observerModularTime.overlapLinks[270]"},{"linkId":null,"sourcePath":"observerModularTime.overlapLinks[271]"},{"linkId":null,"sourcePath":"observerModularTime.overlapLinks[272]"},{"linkId":null,"sourcePath":"observerModularTime.overlapLinks[273]"},{"linkId":null,"sourcePath":"observerModularTime.overlapLinks[274]"},{"linkId":null,"sourcePath":"observerModularTime.overlapLinks[275]"},{"linkId":null,"sourcePath":"observerModularTime.overlapLinks[276]"},{"linkId":null,"sourcePath":"observerModularTime.overlapLinks[277]"},{"linkId":null,"sourcePath":"observerModularTime.overlapLinks[278]"},{"linkId":null,"sourcePath":"observerModularTime.overlapLinks[279]"},{"linkId":null,"sourcePath":"observerModularTime.overlapLinks[280]"},{"linkId":null,"sourcePath":"observerModularTime.overlapLinks[281]"},{"linkId":null,"sourcePath":"observerModularTime.overlapLinks[282]"},{"linkId":null,"sourcePath":"observerModularTime.overlapLinks[283]"},{"linkId":null,"sourcePath":"observerModularTime.overlapLinks[284]"},{"linkId":null,"sourcePath":"observerModularTime.overlapLinks[285]"},{"linkId":null,"sourcePath":"observerModularTime.overlapLinks[286]"},{"linkId":null,"sourcePath":"observerModularTime.overlapLinks[287]"},{"linkId":null,"sourcePath":"observerModularTime.overlapLinks[288]"},{"linkId":null,"sourcePath":"observerModularTime.overlapLinks[289]"},{"linkId":null,"sourcePath":"observerModularTime.overlapLinks[290]"},{"linkId":null,"sourcePath":"observerModularTime.overlapLinks[291]"},{"linkId":null,"sourcePath":"observerModularTime.overlapLinks[292]"},{"linkId":null,"sourcePath":"observerModularTime.overlapLinks[293]"},{"linkId":null,"sourcePath":"observerModularTime.overlapLinks[294]"},{"linkId":null,"sourcePath":"observerModularTime.overlapLinks[295]"},{"linkId":null,"sourcePath":"observerModularTime.overlapLinks[296]"},{"linkId":null,"sourcePath":"observerModularTime.overlapLinks[297]"},{"linkId":null,"sourcePath":"observerModularTime.overlapLinks[298]"}],"shotList":[{"cameraId":"subjective_observer_276","observerId":276,"frameCount":96,"supportPatchCount":96,"firstVisibleReadoutHash":"a0a9b2f65a5782a5","lastVisibleReadoutHash":"a0a9b2f65a5782a5","visibleProtoWorldlineIds":["worldline_000001","worldline_000010","worldline_000021","worldline_000067","worldline_000070","worldline_000106","worldline_000119","worldline_000140","worldline_000152","worldline_000157","worldline_000158","worldline_000160","worldline_000173","worldline_000193","worldline_000211","worldline_000228","worldline_000293","worldline_000303","worldline_000320","worldline_000321","worldline_000363","worldline_000366","worldline_000392","worldline_000433","worldline_000434","worldline_000436","worldline_000478","worldline_000498","worldline_000518"],"visibleProtoWorldlineSightingCount":1536,"suggestedUse":"first_person_observer_readout_track"},{"cameraId":"subjective_observer_503","observerId":503,"frameCount":96,"supportPatchCount":96,"firstVisibleReadoutHash":"1ac338d676039c2a","lastVisibleReadoutHash":"1ac338d676039c2a","visibleProtoWorldlineIds":["worldline_000001","worldline_000010","worldline_000049","worldline_000067","worldline_000070","worldline_000095","worldline_000106","worldline_000119","worldline_000140","worldline_000152","worldline_000158","worldline_000173","worldline_000193","worldline_000211","worldline_000274","worldline_000293","worldline_000299","worldline_000303","worldline_000320","worldline_000335","worldline_000363","worldline_000366","worldline_000377","worldline_000406","worldline_000433","worldline_000434","worldline_000436","worldline_000478","worldline_000484","worldline_000518"],"visibleProtoWorldlineSightingCount":1536,"suggestedUse":"first_person_observer_readout_track"},{"cameraId":"subjective_observer_522","observerId":522,"frameCount":96,"supportPatchCount":96,"firstVisibleReadoutHash":"feecf6a783f001ff","lastVisibleReadoutHash":"feecf6a783f001ff","visibleProtoWorldlineIds":["worldline_000001","worldline_000021","worldline_000049","worldline_000070","worldline_000106","worldline_000119","worldline_000140","worldline_000152","worldline_000157","worldline_000158","worldline_000160","worldline_000173","worldline_000193","worldline_000211","worldline_000228","worldline_000293","worldline_000303","worldline_000320","worldline_000321","worldline_000363","worldline_000366","worldline_000392","worldline_000433","worldline_000434","worldline_000436","worldline_000478","worldline_000484","worldline_000498","worldline_000518"],"visibleProtoWorldlineSightingCount":1536,"suggestedUse":"first_person_observer_readout_track"},{"cameraId":"subjective_observer_535","observerId":535,"frameCount":96,"supportPatchCount":96,"firstVisibleReadoutHash":"02cba4a3916aabec","lastVisibleReadoutHash":"02cba4a3916aabec","visibleProtoWorldlineIds":["worldline_000001","worldline_000021","worldline_000049","worldline_000070","worldline_000106","worldline_000119","worldline_000140","worldline_000152","worldline_000157","worldline_000158","worldline_000160","worldline_000173","worldline_000193","worldline_000211","worldline_000228","worldline_000293","worldline_000303","worldline_000320","worldline_000321","worldline_000363","worldline_000366","worldline_000392","worldline_000433","worldline_000434","worldline_000436","worldline_000478","worldline_000484","worldline_000498","worldline_000518"],"visibleProtoWorldlineSightingCount":1536,"suggestedUse":"first_person_observer_readout_track"},{"cameraId":"subjective_observer_579","observerId":579,"frameCount":96,"supportPatchCount":96,"firstVisibleReadoutHash":"e12172ff9b38ebd8","lastVisibleReadoutHash":"e12172ff9b38ebd8","visibleProtoWorldlineIds":["worldline_000010","worldline_000049","worldline_000067","worldline_000070","worldline_000095","worldline_000106","worldline_000119","worldline_000140","worldline_000152","worldline_000158","worldline_000173","worldline_000193","worldline_000211","worldline_000274","worldline_000280","worldline_000293","worldline_000299","worldline_000303","worldline_000320","worldline_000321","worldline_000335","worldline_000363","worldline_000366","worldline_000433","worldline_000434","worldline_000436","worldline_000443","worldline_000478","worldline_000484","worldline_000518"],"visibleProtoWorldlineSightingCount":1536,"suggestedUse":"first_person_observer_readout_track"},{"cameraId":"subjective_observer_609","observerId":609,"frameCount":96,"supportPatchCount":96,"firstVisibleReadoutHash":"40be2a0e9fd36f9d","lastVisibleReadoutHash":"40be2a0e9fd36f9d","visibleProtoWorldlineIds":["worldline_000001","worldline_000010","worldline_000021","worldline_000049","worldline_000067","worldline_000070","worldline_000095","worldline_000106","worldline_000119","worldline_000140","worldline_000152","worldline_000157","worldline_000158","worldline_000178","worldline_000228","worldline_000284","worldline_000293","worldline_000303","worldline_000320","worldline_000321","worldline_000363","worldline_000366","worldline_000377","worldline_000392","worldline_000433","worldline_000434","worldline_000436","worldline_000478","worldline_000498"],"visibleProtoWorldlineSightingCount":1536,"suggestedUse":"first_person_observer_readout_track"},{"cameraId":"subjective_observer_615","observerId":615,"frameCount":96,"supportPatchCount":96,"firstVisibleReadoutHash":"918c71176e3fa21f","lastVisibleReadoutHash":"918c71176e3fa21f","visibleProtoWorldlineIds":["worldline_000001","worldline_000010","worldline_000067","worldline_000070","worldline_000095","worldline_000106","worldline_000119","worldline_000140","worldline_000152","worldline_000158","worldline_000178","worldline_000186","worldline_000191","worldline_000280","worldline_000284","worldline_000293","worldline_000294","worldline_000303","worldline_000320","worldline_000334","worldline_000366","worldline_000377","worldline_000406","worldline_000433","worldline_000434","worldline_000436","worldline_000452","worldline_000464","worldline_000478","worldline_000498"],"visibleProtoWorldlineSightingCount":1536,"suggestedUse":"first_person_observer_readout_track"},{"cameraId":"subjective_observer_631","observerId":631,"frameCount":96,"supportPatchCount":96,"firstVisibleReadoutHash":"d45bf62a6fc9749c","lastVisibleReadoutHash":"d45bf62a6fc9749c","visibleProtoWorldlineIds":["worldline_000001","worldline_000010","worldline_000067","worldline_000070","worldline_000095","worldline_000106","worldline_000119","worldline_000140","worldline_000152","worldline_000158","worldline_000173","worldline_000178","worldline_000193","worldline_000211","worldline_000274","worldline_000284","worldline_000293","worldline_000294","worldline_000299","worldline_000303","worldline_000320","worldline_000335","worldline_000366","worldline_000377","worldline_000406","worldline_000433","worldline_000434","worldline_000436","worldline_000452","worldline_000464","worldline_000478","worldline_000484","worldline_000498","worldline_000518"],"visibleProtoWorldlineSightingCount":1536,"suggestedUse":"first_person_observer_readout_track"},{"cameraId":"subjective_observer_776","observerId":776,"frameCount":96,"supportPatchCount":96,"firstVisibleReadoutHash":"b33dae9a4599036b","lastVisibleReadoutHash":"b33dae9a4599036b","visibleProtoWorldlineIds":["worldline_000001","worldline_000021","worldline_000049","worldline_000070","worldline_000106","worldline_000119","worldline_000140","worldline_000152","worldline_000157","worldline_000158","worldline_000160","worldline_000173","worldline_000193","worldline_000211","worldline_000228","worldline_000293","worldline_000303","worldline_000320","worldline_000321","worldline_000363","worldline_000366","worldline_000392","worldline_000433","worldline_000434","worldline_000436","worldline_000478","worldline_000484","worldline_000498","worldline_000518"],"visibleProtoWorldlineSightingCount":1536,"suggestedUse":"first_person_observer_readout_track"},{"cameraId":"subjective_observer_841","observerId":841,"frameCount":96,"supportPatchCount":96,"firstVisibleReadoutHash":"f77341d45a4de104","lastVisibleReadoutHash":"f77341d45a4de104","visibleProtoWorldlineIds":["worldline_000001","worldline_000049","worldline_000070","worldline_000106","worldline_000119","worldline_000140","worldline_000152","worldline_000157","worldline_000158","worldline_000173","worldline_000193","worldline_000211","worldline_000228","worldline_000274","worldline_000280","worldline_000293","worldline_000299","worldline_000303","worldline_000320","worldline_000321","worldline_000335","worldline_000363","worldline_000366","worldline_000392","worldline_000433","worldline_000434","worldline_000436","worldline_000443","worldline_000478","worldline_000484","worldline_000498","worldline_000518"],"visibleProtoWorldlineSightingCount":1536,"suggestedUse":"first_person_observer_readout_track"},{"cameraId":"subjective_observer_868","observerId":868,"frameCount":96,"supportPatchCount":96,"firstVisibleReadoutHash":"ba8f080dc53865b3","lastVisibleReadoutHash":"ba8f080dc53865b3","visibleProtoWorldlineIds":["worldline_000001","worldline_000010","worldline_000021","worldline_000049","worldline_000067","worldline_000070","worldline_000095","worldline_000106","worldline_000117","worldline_000119","worldline_000140","worldline_000152","worldline_000157","worldline_000158","worldline_000160","worldline_000178","worldline_000228","worldline_000284","worldline_000293","worldline_000303","worldline_000320","worldline_000321","worldline_000363","worldline_000366","worldline_000392","worldline_000433","worldline_000434","worldline_000436","worldline_000478","worldline_000498"],"visibleProtoWorldlineSightingCount":1536,"suggestedUse":"first_person_observer_readout_track"},{"cameraId":"subjective_observer_1178","observerId":1178,"frameCount":96,"supportPatchCount":96,"firstVisibleReadoutHash":"bd2b0b156838f794","lastVisibleReadoutHash":"bd2b0b156838f794","visibleProtoWorldlineIds":["worldline_000001","worldline_000010","worldline_000067","worldline_000070","worldline_000095","worldline_000106","worldline_000119","worldline_000140","worldline_000152","worldline_000158","worldline_000173","worldline_000178","worldline_000186","worldline_000191","worldline_000193","worldline_000211","worldline_000284","worldline_000293","worldline_000294","worldline_000303","worldline_000320","worldline_000366","worldline_000377","worldline_000406","worldline_000433","worldline_000434","worldline_000436","worldline_000452","worldline_000464","worldline_000478","worldline_000498","worldline_000518"],"visibleProtoWorldlineSightingCount":1536,"suggestedUse":"first_person_observer_readout_track"},{"cameraId":"subjective_observer_1282","observerId":1282,"frameCount":96,"supportPatchCount":96,"firstVisibleReadoutHash":"b92c8c349efd69a3","lastVisibleReadoutHash":"b92c8c349efd69a3","visibleProtoWorldlineIds":["worldline_000001","worldline_000010","worldline_000049","worldline_000067","worldline_000070","worldline_000075","worldline_000095","worldline_000106","worldline_000117","worldline_000119","worldline_000140","worldline_000152","worldline_000157","worldline_000158","worldline_000178","worldline_000186","worldline_000284","worldline_000293","worldline_000303","worldline_000320","worldline_000321","worldline_000363","worldline_000366","worldline_000377","worldline_000392","worldline_000406","worldline_000433","worldline_000434","worldline_000436","worldline_000452","worldline_000464","worldline_000478","worldline_000498"],"visibleProtoWorldlineSightingCount":1536,"suggestedUse":"first_person_observer_readout_track"},{"cameraId":"subjective_observer_1314","observerId":1314,"frameCount":96,"supportPatchCount":96,"firstVisibleReadoutHash":"bfa1af2cb7cd141e","lastVisibleReadoutHash":"bfa1af2cb7cd141e","visibleProtoWorldlineIds":["worldline_000001","worldline_000010","worldline_000067","worldline_000070","worldline_000095","worldline_000106","worldline_000119","worldline_000140","worldline_000152","worldline_000158","worldline_000178","worldline_000186","worldline_000191","worldline_000284","worldline_000293","worldline_000294","worldline_000303","worldline_000320","worldline_000334","worldline_000366","worldline_000377","worldline_000406","worldline_000433","worldline_000434","worldline_000436","worldline_000452","worldline_000464","worldline_000478","worldline_000498"],"visibleProtoWorldlineSightingCount":1536,"suggestedUse":"first_person_observer_readout_track"},{"cameraId":"subjective_observer_1395","observerId":1395,"frameCount":96,"supportPatchCount":96,"firstVisibleReadoutHash":"4254bce96ba4f868","lastVisibleReadoutHash":"4254bce96ba4f868","visibleProtoWorldlineIds":["worldline_000001","worldline_000010","worldline_000067","worldline_000070","worldline_000095","worldline_000106","worldline_000119","worldline_000140","worldline_000152","worldline_000158","worldline_000178","worldline_000186","worldline_000191","worldline_000284","worldline_000293","worldline_000294","worldline_000303","worldline_000320","worldline_000321","worldline_000334","worldline_000377","worldline_000406","worldline_000433","worldline_000434","worldline_000436","worldline_000452","worldline_000464","worldline_000478","worldline_000498"],"visibleProtoWorldlineSightingCount":1536,"suggestedUse":"first_person_observer_readout_track"},{"cameraId":"subjective_observer_1421","observerId":1421,"frameCount":96,"supportPatchCount":96,"firstVisibleReadoutHash":"9630336cf084dcba","lastVisibleReadoutHash":"9630336cf084dcba","visibleProtoWorldlineIds":["worldline_000001","worldline_000010","worldline_000067","worldline_000070","worldline_000095","worldline_000106","worldline_000119","worldline_000140","worldline_000152","worldline_000158","worldline_000178","worldline_000186","worldline_000191","worldline_000284","worldline_000293","worldline_000294","worldline_000303","worldline_000320","worldline_000321","worldline_000334","worldline_000366","worldline_000377","worldline_000406","worldline_000433","worldline_000434","worldline_000436","worldline_000452","worldline_000464","worldline_000478","worldline_000498"],"visibleProtoWorldlineSightingCount":1536,"suggestedUse":"first_person_observer_readout_track"},{"cameraId":"subjective_observer_1558","observerId":1558,"frameCount":96,"supportPatchCount":96,"firstVisibleReadoutHash":"8c11441e42802558","lastVisibleReadoutHash":"8c11441e42802558","visibleProtoWorldlineIds":["worldline_000012","worldline_000049","worldline_000061","worldline_000070","worldline_000106","worldline_000119","worldline_000140","worldline_000152","worldline_000158","worldline_000173","worldline_000184","worldline_000185","worldline_000193","worldline_000211","worldline_000221","worldline_000274","worldline_000280","worldline_000293","worldline_000299","worldline_000303","worldline_000320","worldline_000321","worldline_000335","worldline_000366","worldline_000433","worldline_000434","worldline_000436","worldline_000443","worldline_000478","worldline_000484","worldline_000518"],"visibleProtoWorldlineSightingCount":1536,"suggestedUse":"first_person_observer_readout_track"},{"cameraId":"subjective_observer_1638","observerId":1638,"frameCount":96,"supportPatchCount":96,"firstVisibleReadoutHash":"677e5e01242196e2","lastVisibleReadoutHash":"677e5e01242196e2","visibleProtoWorldlineIds":["worldline_000001","worldline_000010","worldline_000049","worldline_000067","worldline_000070","worldline_000075","worldline_000095","worldline_000106","worldline_000117","worldline_000119","worldline_000140","worldline_000152","worldline_000157","worldline_000158","worldline_000178","worldline_000228","worldline_000284","worldline_000293","worldline_000303","worldline_000320","worldline_000321","worldline_000363","worldline_000366","worldline_000377","worldline_000392","worldline_000406","worldline_000433","worldline_000434","worldline_000436","worldline_000478","worldline_000498"],"visibleProtoWorldlineSightingCount":1536,"suggestedUse":"first_person_observer_readout_track"},{"cameraId":"subjective_observer_1648","observerId":1648,"frameCount":96,"supportPatchCount":96,"firstVisibleReadoutHash":"ed48d8f9cd42b93c","lastVisibleReadoutHash":"ed48d8f9cd42b93c","visibleProtoWorldlineIds":["worldline_000001","worldline_000010","worldline_000021","worldline_000049","worldline_000067","worldline_000070","worldline_000075","worldline_000095","worldline_000106","worldline_000117","worldline_000119","worldline_000140","worldline_000152","worldline_000157","worldline_000158","worldline_000160","worldline_000178","worldline_000228","worldline_000273","worldline_000293","worldline_000303","worldline_000320","worldline_000321","worldline_000363","worldline_000366","worldline_000392","worldline_000433","worldline_000434","worldline_000436","worldline_000478","worldline_000498"],"visibleProtoWorldlineSightingCount":1536,"suggestedUse":"first_person_observer_readout_track"},{"cameraId":"subjective_observer_1674","observerId":1674,"frameCount":96,"supportPatchCount":96,"firstVisibleReadoutHash":"114aea7e8647f353","lastVisibleReadoutHash":"114aea7e8647f353","visibleProtoWorldlineIds":["worldline_000001","worldline_000021","worldline_000049","worldline_000070","worldline_000106","worldline_000119","worldline_000140","worldline_000152","worldline_000157","worldline_000158","worldline_000160","worldline_000173","worldline_000193","worldline_000211","worldline_000228","worldline_000273","worldline_000293","worldline_000303","worldline_000320","worldline_000321","worldline_000363","worldline_000366","worldline_000392","worldline_000433","worldline_000434","worldline_000436","worldline_000478","worldline_000498"],"visibleProtoWorldlineSightingCount":1536,"suggestedUse":"first_person_observer_readout_track"},{"cameraId":"subjective_observer_1705","observerId":1705,"frameCount":96,"supportPatchCount":96,"firstVisibleReadoutHash":"44a08163beb11ebb","lastVisibleReadoutHash":"44a08163beb11ebb","visibleProtoWorldlineIds":["worldline_000021","worldline_000049","worldline_000070","worldline_000106","worldline_000119","worldline_000152","worldline_000157","worldline_000158","worldline_000173","worldline_000193","worldline_000211","worldline_000228","worldline_000274","worldline_000293","worldline_000299","worldline_000303","worldline_000320","worldline_000321","worldline_000335","worldline_000363","worldline_000366","worldline_000392","worldline_000433","worldline_000434","worldline_000436","worldline_000478","worldline_000484","worldline_000518"],"visibleProtoWorldlineSightingCount":1536,"suggestedUse":"first_person_observer_readout_track"},{"cameraId":"subjective_observer_1755","observerId":1755,"frameCount":96,"supportPatchCount":96,"firstVisibleReadoutHash":"a0cd8f15f83aaf97","lastVisibleReadoutHash":"a0cd8f15f83aaf97","visibleProtoWorldlineIds":["worldline_000001","worldline_000021","worldline_000049","worldline_000070","worldline_000106","worldline_000119","worldline_000152","worldline_000157","worldline_000158","worldline_000160","worldline_000173","worldline_000193","worldline_000211","worldline_000228","worldline_000273","worldline_000274","worldline_000293","worldline_000303","worldline_000320","worldline_000321","worldline_000363","worldline_000366","worldline_000392","worldline_000433","worldline_000434","worldline_000436","worldline_000478","worldline_000484","worldline_000498","worldline_000518"],"visibleProtoWorldlineSightingCount":1536,"suggestedUse":"first_person_observer_readout_track"},{"cameraId":"subjective_observer_1814","observerId":1814,"frameCount":96,"supportPatchCount":96,"firstVisibleReadoutHash":"09b34dcf2490c44b","lastVisibleReadoutHash":"09b34dcf2490c44b","visibleProtoWorldlineIds":["worldline_000001","worldline_000010","worldline_000067","worldline_000070","worldline_000095","worldline_000106","worldline_000119","worldline_000140","worldline_000152","worldline_000158","worldline_000178","worldline_000186","worldline_000191","worldline_000284","worldline_000293","worldline_000294","worldline_000303","worldline_000320","worldline_000334","worldline_000377","worldline_000406","worldline_000433","worldline_000434","worldline_000436","worldline_000452","worldline_000464","worldline_000478","worldline_000498"],"visibleProtoWorldlineSightingCount":1536,"suggestedUse":"first_person_observer_readout_track"},{"cameraId":"subjective_observer_1850","observerId":1850,"frameCount":96,"supportPatchCount":96,"firstVisibleReadoutHash":"2684d4306d840640","lastVisibleReadoutHash":"2684d4306d840640","visibleProtoWorldlineIds":["worldline_000001","worldline_000010","worldline_000021","worldline_000049","worldline_000067","worldline_000070","worldline_000075","worldline_000095","worldline_000106","worldline_000117","worldline_000119","worldline_000140","worldline_000152","worldline_000157","worldline_000158","worldline_000160","worldline_000178","worldline_000228","worldline_000284","worldline_000293","worldline_000303","worldline_000320","worldline_000321","worldline_000363","worldline_000366","worldline_000392","worldline_000433","worldline_000434","worldline_000436","worldline_000478","worldline_000498"],"visibleProtoWorldlineSightingCount":1536,"suggestedUse":"first_person_observer_readout_track"},{"cameraId":"subjective_observer_1852","observerId":1852,"frameCount":96,"supportPatchCount":96,"firstVisibleReadoutHash":"e46e48b0e766c2b9","lastVisibleReadoutHash":"e46e48b0e766c2b9","visibleProtoWorldlineIds":["worldline_000001","worldline_000021","worldline_000049","worldline_000070","worldline_000106","worldline_000119","worldline_000140","worldline_000152","worldline_000157","worldline_000158","worldline_000160","worldline_000173","worldline_000193","worldline_000211","worldline_000228","worldline_000273","worldline_000293","worldline_000303","worldline_000320","worldline_000321","worldline_000363","worldline_000366","worldline_000392","worldline_000433","worldline_000434","worldline_000436","worldline_000478","worldline_000498","worldline_000518"],"visibleProtoWorldlineSightingCount":1536,"suggestedUse":"first_person_observer_readout_track"},{"cameraId":"subjective_observer_1877","observerId":1877,"frameCount":96,"supportPatchCount":96,"firstVisibleReadoutHash":"e8b1c382c7f73ed3","lastVisibleReadoutHash":"e8b1c382c7f73ed3","visibleProtoWorldlineIds":["worldline_000001","worldline_000010","worldline_000067","worldline_000070","worldline_000095","worldline_000106","worldline_000119","worldline_000140","worldline_000152","worldline_000158","worldline_000173","worldline_000178","worldline_000186","worldline_000191","worldline_000193","worldline_000211","worldline_000284","worldline_000293","worldline_000294","worldline_000303","worldline_000320","worldline_000366","worldline_000377","worldline_000406","worldline_000433","worldline_000434","worldline_000436","worldline_000452","worldline_000464","worldline_000478","worldline_000498"],"visibleProtoWorldlineSightingCount":1536,"suggestedUse":"first_person_observer_readout_track"},{"cameraId":"subjective_observer_1987","observerId":1987,"frameCount":96,"supportPatchCount":96,"firstVisibleReadoutHash":"f073aa25106f28c9","lastVisibleReadoutHash":"f073aa25106f28c9","visibleProtoWorldlineIds":["worldline_000010","worldline_000067","worldline_000070","worldline_000095","worldline_000106","worldline_000119","worldline_000140","worldline_000152","worldline_000158","worldline_000173","worldline_000178","worldline_000186","worldline_000191","worldline_000193","worldline_000211","worldline_000284","worldline_000293","worldline_000294","worldline_000303","worldline_000320","worldline_000366","worldline_000377","worldline_000406","worldline_000433","worldline_000434","worldline_000436","worldline_000452","worldline_000464","worldline_000478","worldline_000518"],"visibleProtoWorldlineSightingCount":1536,"suggestedUse":"first_person_observer_readout_track"},{"cameraId":"subjective_observer_2048","observerId":2048,"frameCount":96,"supportPatchCount":96,"firstVisibleReadoutHash":"d9bae34e4cfe6988","lastVisibleReadoutHash":"d9bae34e4cfe6988","visibleProtoWorldlineIds":["worldline_000021","worldline_000049","worldline_000070","worldline_000106","worldline_000119","worldline_000152","worldline_000157","worldline_000158","worldline_000160","worldline_000173","worldline_000193","worldline_000211","worldline_000228","worldline_000274","worldline_000293","worldline_000303","worldline_000320","worldline_000321","worldline_000363","worldline_000366","worldline_000392","worldline_000433","worldline_000434","worldline_000436","worldline_000478","worldline_000484","worldline_000518"],"visibleProtoWorldlineSightingCount":1536,"suggestedUse":"first_person_observer_readout_track"},{"cameraId":"subjective_observer_2123","observerId":2123,"frameCount":96,"supportPatchCount":96,"firstVisibleReadoutHash":"bb1d4e2ff0a994fc","lastVisibleReadoutHash":"bb1d4e2ff0a994fc","visibleProtoWorldlineIds":["worldline_000001","worldline_000010","worldline_000067","worldline_000070","worldline_000095","worldline_000106","worldline_000119","worldline_000140","worldline_000152","worldline_000158","worldline_000178","worldline_000186","worldline_000191","worldline_000284","worldline_000293","worldline_000294","worldline_000303","worldline_000320","worldline_000334","worldline_000377","worldline_000406","worldline_000433","worldline_000434","worldline_000436","worldline_000452","worldline_000464","worldline_000478","worldline_000498"],"visibleProtoWorldlineSightingCount":1536,"suggestedUse":"first_person_observer_readout_track"},{"cameraId":"subjective_observer_2161","observerId":2161,"frameCount":96,"supportPatchCount":96,"firstVisibleReadoutHash":"277f86acf242ab08","lastVisibleReadoutHash":"277f86acf242ab08","visibleProtoWorldlineIds":["worldline_000001","worldline_000021","worldline_000049","worldline_000070","worldline_000106","worldline_000117","worldline_000119","worldline_000140","worldline_000152","worldline_000157","worldline_000158","worldline_000160","worldline_000173","worldline_000193","worldline_000211","worldline_000228","worldline_000273","worldline_000293","worldline_000303","worldline_000320","worldline_000321","worldline_000363","worldline_000366","worldline_000392","worldline_000433","worldline_000434","worldline_000436","worldline_000478","worldline_000498"],"visibleProtoWorldlineSightingCount":1536,"suggestedUse":"first_person_observer_readout_track"},{"cameraId":"subjective_observer_2170","observerId":2170,"frameCount":96,"supportPatchCount":96,"firstVisibleReadoutHash":"8c9bd70f5bc3a83b","lastVisibleReadoutHash":"8c9bd70f5bc3a83b","visibleProtoWorldlineIds":["worldline_000001","worldline_000010","worldline_000067","worldline_000070","worldline_000095","worldline_000106","worldline_000119","worldline_000140","worldline_000152","worldline_000158","worldline_000178","worldline_000186","worldline_000191","worldline_000284","worldline_000293","worldline_000294","worldline_000303","worldline_000320","worldline_000321","worldline_000334","worldline_000377","worldline_000406","worldline_000433","worldline_000434","worldline_000436","worldline_000452","worldline_000464","worldline_000478","worldline_000498"],"visibleProtoWorldlineSightingCount":1536,"suggestedUse":"first_person_observer_readout_track"},{"cameraId":"subjective_observer_2266","observerId":2266,"frameCount":96,"supportPatchCount":96,"firstVisibleReadoutHash":"a65d6c3531c9ed72","lastVisibleReadoutHash":"a65d6c3531c9ed72","visibleProtoWorldlineIds":["worldline_000001","worldline_000010","worldline_000021","worldline_000049","worldline_000067","worldline_000070","worldline_000075","worldline_000095","worldline_000106","worldline_000117","worldline_000119","worldline_000140","worldline_000152","worldline_000157","worldline_000158","worldline_000160","worldline_000178","worldline_000228","worldline_000273","worldline_000293","worldline_000303","worldline_000320","worldline_000321","worldline_000363","worldline_000366","worldline_000392","worldline_000433","worldline_000434","worldline_000436","worldline_000478","worldline_000498"],"visibleProtoWorldlineSightingCount":1536,"suggestedUse":"first_person_observer_readout_track"}],"availability":{"observerViewCount":128,"subjectiveCameraCount":128,"globalTimelineFrameCount":128,"cameraFrameCount":12288,"protoWorldlineSightingCount":196608,"peripheralDiagnosticSightingCount":196608,"protoWorldlineVisibleCameraCount":128,"overlapLinkCount":299},"receipts":{"observer_modular_time_receipt":true,"observer_facing_3p1d_h3_experience_receipt":false,"observer_facing_populated_h3_experience_receipt":false,"observer_h3_object_population_receipt":false,"support_visible_lorentz_3p1_kinematics_receipt":true,"conformal_h3_spatial_chart_receipt":true,"bulk_3d_established":false},"claimBoundary":"Observer cinema is first-person/local readout rendering. It is not an omniscient global camera or objective global time coordinate. Large arrays live only at their canonical top-level paths; this section contains stable references and shot summaries."}